SAF/__init__.py
SAF/version.py
SAF/features/generator.py
SAF/features/coordination/binary.py
SAF/features/coordination/helper.py
SAF/features/coordination/quaternary.py
SAF/features/coordination/ternary.py
SAF/features/environment/binary.py
SAF/features/environment/binary_helper.py
SAF/features/environment/quaternary.py
SAF/features/environment/quaternary_helper.py
SAF/features/environment/ternary.py
SAF/features/environment/ternary_helper.py
SAF/features/environment/util.py
SAF/features/interatomic/binary.py
SAF/features/interatomic/helper.py
SAF/features/interatomic/quaternary.py
SAF/features/interatomic/ternary.py
SAF/features/wyc/binary.py
SAF/features/wyc/helper.py
SAF/features/wyc/quaternary.py
SAF/features/wyc/ternary.py
SAF/utils/bond.py
SAF/utils/packing.py
structure_analyzer_featurizer-0.0.1.dist-info/licenses/AUTHORS.rst
structure_analyzer_featurizer-0.0.1.dist-info/licenses/LICENSE.rst
structure_analyzer_featurizer-0.0.1.dist-info/METADATA
structure_analyzer_featurizer-0.0.1.dist-info/WHEEL
structure_analyzer_featurizer-0.0.1.dist-info/top_level.txt
structure_analyzer_featurizer-0.0.1.dist-info/RECORD
